{
  "log": {
#    "access": "/var/log/xray/access.log",
#    "error": "/var/log/xray/error.log",
#    "dnsLog": false,
    "loglevel": "warning"
  },
  "inbounds": [
    {
      "port": 443,
      "protocol": "vless",
      "settings": {
        "clients": [
          {
            "id": "youruuuuuuuuuuuuuid",
            "level": 0,
            "email": "love@example.com",
            "flow": "xtls-rprx-direct"
          }
        ],
        "decryption": "none",
        "fallbacks": [
          {
            "dest": 80,
            "xver": 1
          }
        ]
      },
      "streamSettings": {
        "network": "tcp",
        "security": "xtls",
        "xtlsSettings": {
          "serverName": "yourservername",
          "allowInsecure": false,
#          "alpn": ["h2", "http/1.1"],
#          "fingerprint": "randomized",
          "certificates": [
            {
              "certificateFile": "/usr/local/nginx/conf/ssl/yourservername/fullchain.cer",
              "keyFile": "/usr/local/nginx/conf/ssl/yourservername/yourservername.key"
            }
          ]
        }
      }
    }
  ],
  "outbounds": [
    {
#      "mux": {
#        "enabled": false,
#        "concurrency": 8
#      },
      "protocol": "freedom"
    }
  ]
}
